govnoscript/__init__.py
govnoscript/core.py
govnoscript-1.1.1.dist-info/METADATA
govnoscript-1.1.1.dist-info/WHEEL
govnoscript-1.1.1.dist-info/RECORD
