Metadata-Version: 2.4
Name: govnoscript
Version: 1.1.1
Summary: A simple scripting language for computer control
License: MIT
Author: dertfin1
Author-email: dertfin@gmail.com
Requires-Python: >=3.11
Classifier: License :: OSI Approved :: MIT License
Classifier: Programming Language :: Python :: 3
Classifier: Programming Language :: Python :: 3.11
Classifier: Programming Language :: Python :: 3.12
Classifier: Programming Language :: Python :: 3.13
Classifier: Programming Language :: Python :: 3.14
Requires-Dist: keyboard (>=0.13.5,<0.14.0)
Requires-Dist: pyautogui (>=0.9.54,<0.10.0)
